flask_status/__init__.py
flask_status/main.py
Flask_Status-1.0.1.dist-info/LICENSE
Flask_Status-1.0.1.dist-info/METADATA
Flask_Status-1.0.1.dist-info/WHEEL
Flask_Status-1.0.1.dist-info/top_level.txt
Flask_Status-1.0.1.dist-info/RECORD
