Metadata-Version: 2.1
Name: Flask-Status
Version: 1.0.1
Summary: Add status ping route to your Flask Server
Home-page: https://github.com/Emmo00/flask-status
Author: Nwafor Emmanuel
Author-email: nwaforemmanuel005@gmail.com
Keywords: flask ping,status ping,status,ping,flask
Classifier: Programming Language :: Python :: 3
Classifier: License :: OSI Approved :: MIT License
Classifier: Operating System :: OS Independent
Requires-Python: >=3.7
License-File: LICENSE
Requires-Dist: flask
